liweather.py
liweather-0.1.4.dist-info/METADATA
liweather-0.1.4.dist-info/WHEEL
liweather-0.1.4.dist-info/entry_points.txt
liweather-0.1.4.dist-info/RECORD
