Metadata-Version: 2.4
Name: liweather
Version: 0.1.4
Summary: Add your description here
Requires-Python: >=3.13
Requires-Dist: build>=1.2.2.post1
Requires-Dist: mcp[cli]>=1.10.1
Requires-Dist: twine>=6.1.0
